{
  "asset": {
    "font": {
      "icon": {
        "name": "Nantes",
        "woff": "https://etldev.blob.core.windows.net/fonts/Nantes-Regular.woff"
      }
    }
  },
  "color": {
    "base": {
      "white": "#ffffff",
      "black": "#000000",
      "gray": {
        "50": "#f9f7fc",
        "100": "#efeff4",
        "200": "#e2e2ed",
        "300": "#e4e4ea",
        "400": "#d1d0d8",
        "500": "#b2b1bc",
        "600": "#9999a3",
        "700": "#7d7c84",
        "800": "#535156",
        "900": "#3c3b3f",
        "1000": "#242326"
      },
      "yellow": {
        "bright": "#fdff00",
        "deep": "#ef9b0d",
        "light": "#fdff00",
        "pastel": "#f1ffcf",
        "primary": "#fded35"
      },
      "lime": {
        "bright": "#64ff00",
        "deep": "#58e86b",
        "light": "#a8f36a",
        "pastel": "#d4ffdc",
        "primary": "#78ec6c"
      },
      "green": {
        "bright": "#54ff95",
        "deep": "#006e59",
        "light": "#61ecb2",
        "pastel": "#cef4d1",
        "primary": "#00b459"
      },
      "teal": {
        "bright": "#00ffe4",
        "deep": "#205273",
        "light": "#00cec8",
        "pastel": "#c4f7f4",
        "primary": "#57b5b1"
      },
      "blue": {
        "bright": "#0000ff",
        "deep": "#000045",
        "light": "#3cd8ff",
        "pastel": "#a0e5f7",
        "primary": "#2d76cc"
      },
      "violet": {
        "bright": "#6b00d7",
        "deep": "#190087",
        "light": "#0f358e",
        "pastel": "#5172bf",
        "primary": "#0f358e"
      },
      "purple": {
        "bright": "#9100ff",
        "deep": "#3e00b3",
        "light": "#d391fa",
        "pastel": "#e5d0ff",
        "primary": "#3e00b3"
      },
      "magenta": {
        "bright": "#ff00ff",
        "deep": "#7e1a65",
        "light": "#e779b8",
        "pastel": "#f4e4db",
        "primary": "#7e1a65"
      },
      "red": {
        "bright": "#ff0000",
        "deep": "#a30000",
        "light": "#ff6434",
        "pastel": "#ffccbc",
        "primary": "#dd2c00"
      },
      "orange": {
        "bright": "#ef7200",
        "deep": "#e55929",
        "light": "#d99566",
        "pastel": "#fff3e0",
        "primary": "#ff5722"
      },
      "golden": {
        "bright": "#f7941d",
        "deep": "#c66900",
        "light": "#ffc947",
        "pastel": "#ffffe4",
        "primary": "#ff9800"
      }
    },
    "heatmap": {
      "first": "rgba(255, 200, 71, 0.8)",
      "second": "rgba(255, 0, 255, 0.8)",
      "third": "rgba(178, 77, 255, 0.8)",
      "fourth": "rgba(161, 230, 247, 0.6)",
      "fifth": "rgba(205, 244, 208, 0.4)",
      "sixth": "#f9f7fc"
    },
    "vibes": {
      "absurd": {
        "primary": "#a8f36a",
        "secondary": "#00ffe4"
      },
      "active": {
        "primary": "#64ff00",
        "secondary": "#c4f7f4"
      },
      "activist": {
        "primary": "#c66900",
        "secondary": "#e779b8"
      },
      "adventurous": {
        "primary": "#00b459",
        "secondary": "#c4f7f4"
      },
      "alternative": {
        "primary": "#f7941d",
        "secondary": "#ffc947"
      },
      "airy": {
        "primary": "#fff3e0",
        "secondary": "#f1ffcf"
      },
      "analog": {
        "primary": "#205273",
        "secondary": "#e55929"
      },
      "antique": {
        "primary": "#d99566",
        "secondary": "#57b5b1"
      },
      "artisanal": {
        "primary": "#ffccbc",
        "secondary": "#cef4d1"
      },
      "architectural": {
        "primary": "#7e1a65",
        "secondary": "#fff3e0"
      },
      "artsy": {
        "primary": "#d391fa",
        "secondary": "#006e59"
      },
      "aquatic": {
        "primary": "#0000ff",
        "secondary": "#00cec8"
      },
      "art": {
        "primary": "#d391fa",
        "secondary": "#00cec8"
      },
      "authentic": {
        "primary": "#ffccbc",
        "secondary": "#ffffe4"
      },
      "aware": {
        "primary": "#9100ff",
        "secondary": "#00ffe4",
        "tertiary": "#fff3e0"
      },
      "beautiful": {
        "primary": "#a0e5f7",
        "secondary": "#ffccbc"
      },
      "belonging": {
        "primary": "#f7941d",
        "secondary": "#ffccbc"
      },
      "blissful": {
        "primary": "#e779b8",
        "secondary": "#f1ffcf"
      },
      "bold": {
        "primary": "#ef7200",
        "secondary": "#f4e4db"
      },
      "boozy": {
        "primary": "#ff5722",
        "secondary": "#dd2c00"
      },
      "botanical": {
        "primary": "#d4ffdc",
        "secondary": "#e5d0ff"
      },
      "bright": {
        "primary": "#fdff00",
        "secondary": "#d4ffdc"
      },
      "busy": {
        "primary": "#e55929",
        "secondary": "#ff9800"
      },
      "buzzing": {
        "primary": "#ff9800",
        "secondary": "#fded35",
        "tertiary": "#c66900"
      },
      "calm": {
        "primary": "#d4ffdc",
        "secondary": "#3cd8ff"
      },
      "celebration": {
        "primary": "#ff9800",
        "secondary": "#f1ffcf"
      },
      "celebratory": {
        "primary": "#ff9800",
        "secondary": "#f1ffcf"
      },
      "charming": {
        "primary": "#5172bf",
        "secondary": "#e5d0ff"
      },
      "cheerful": {
        "primary": "#f4e4db",
        "secondary": "#fff3e0"
      },
      "chill": {
        "primary": "#00ffe4",
        "secondary": "#d4ffdc",
        "tertiary": "#ffffe4"
      },
      "cinematic": {
        "primary": "#205273",
        "secondary": "#d391fa"
      },
      "civic": {
        "primary": "#ff5722",
        "secondary": "#2d76cc"
      },
      "classic": {
        "primary": "#f7941d",
        "secondary": "#c4f7f4"
      },
      "colorful": {
        "primary": "#d391fa",
        "secondary": "#61ecb2"
      },
      "community": {
        "primary": "#ffccbc",
        "secondary": "#e5d0ff"
      },
      "contemplative": {
        "primary": "#a0e5f7",
        "secondary": "#c4f7f4"
      },
      "cool": {
        "primary": "#57b5b1",
        "secondary": "#3cd8ff"
      },
      "courageous": {
        "primary": "#d391fa",
        "secondary": "#fff3e0"
      },
      "collective": {
        "primary": "#f1ffcf",
        "secondary": "#000045"
      },
      "collectable": {
        "primary": "#d391fa",
        "secondary": "#f1ffcf"
      },
      "cozy": {
        "primary": "#ffc947",
        "secondary": "#ef9b0d"
      },
      "cultural": {
        "primary": "#ef9b0d",
        "secondary": "#a0e5f7"
      },
      "curious": {
        "primary": "#54ff95",
        "secondary": "#ef9b0d"
      },
      "cute": {
        "primary": "#e779b8",
        "secondary": "#fded35"
      },
      "creative": {
        "primary": "#a0e5f7",
        "secondary": "#9100ff"
      },
      "crowded": {
        "primary": "#000045",
        "secondary": "#ffccbc"
      },
      "diverse": {
        "primary": "#e5d0ff",
        "secondary": "#00ffe4"
      },
      "dreamy": {
        "primary": "#d391fa",
        "secondary": "#f1ffcf",
        "tertiary": "#a0e5f7"
      },
      "drinking": {
        "primary": "#ff5722",
        "secondary": "#dd2c00"
      },
      "dynamic": {
        "primary": "#9100ff",
        "secondary": "#78ec6c"
      },
      "eclectic": {
        "primary": "#00ffe4",
        "secondary": "#e5d0ff"
      },
      "edgy": {
        "primary": "#0f358e",
        "secondary": "#fff3e0"
      },
      "energetic": {
        "primary": "#ff9800",
        "secondary": "#fded35",
        "tertiary": "#ef9b0d"
      },
      "energy": {
        "primary": "#ff5722",
        "secondary": "#ff9800"
      },
      "exciting": {
        "primary": "#fded35",
        "secondary": "#ff00ff"
      },
      "family": {
        "primary": "#e779b8",
        "secondary": "#a0e5f7"
      },
      "festive": {
        "primary": "#9100ff",
        "secondary": "#ffffe4"
      },
      "fierce": {
        "primary": "#a30000",
        "secondary": "#ffccbc"
      },
      "folk": {
        "primary": "#006e59",
        "secondary": "#ef9b0d"
      },
      "fragrant": {
        "primary": "#cef4d1",
        "secondary": "#d4ffdc"
      },
      "friendly": {
        "primary": "#3cd8ff",
        "secondary": "#d391fa"
      },
      "fun": {
        "primary": "#fded35",
        "secondary": "#d391fa"
      },
      "funny": {
        "primary": "#fdff00",
        "secondary": "#00cec8"
      },
      "generous": {
        "primary": "#ffc947",
        "secondary": "#a8f36a"
      },
      "happy": {
        "primary": "#ef9b0d",
        "secondary": "#d4ffdc"
      },
      "hippie": {
        "primary": "#ff00ff",
        "secondary": "#fded35"
      },
      "historic": {
        "primary": "#c66900",
        "secondary": "#fff3e0"
      },
      "hopeful": {
        "primary": "#f7941d",
        "secondary": "#d4ffdc"
      },
      "inclusive": {
        "primary": "#ff9800",
        "secondary": "#e5d0ff"
      },
      "iconic": {
        "primary": "#7e1a65",
        "secondary": "#f4e4db"
      },
      "inspired": {
        "primary": "#57b5b1",
        "secondary": "#58e86b"
      },
      "intimate": {
        "primary": "#7e1a65",
        "secondary": "#ffccbc"
      },
      "joyful": {
        "primary": "#fdff00",
        "secondary": "#ffc947"
      },
      "legacy": {
        "primary": "#d391fa",
        "secondary": "#a0e5f7"
      },
      "lit": {
        "primary": "#fded35",
        "secondary": "#ff5722"
      },
      "lively": {
        "primary": "#ff5722",
        "secondary": "#a0e5f7"
      },
      "local": {
        "primary": "#ff00ff",
        "secondary": "#a8f36a"
      },
      "loud": {
        "primary": "#64ff00",
        "secondary": "#0000ff"
      },
      "love": {
        "primary": "#ff0000",
        "secondary": "#e5d0ff"
      },
      "magical": {
        "primary": "#fdff00",
        "secondary": "#e779b8"
      },
      "mindful": {
        "primary": "#57b5b1",
        "secondary": "#2d76cc"
      },
      "musical": {
        "primary": "#d391fa",
        "secondary": "#fded35"
      },
      "natural": {
        "primary": "#00b459",
        "secondary": "#ffccbc"
      },
      "neon": {
        "primary": "#64ff00",
        "secondary": "#00ffe4"
      },
      "new": {
        "primary": "#64ff00",
        "secondary": "#e5d0ff"
      },
      "nostalgic": {
        "primary": "#2d76cc",
        "secondary": "#d99566"
      },
      "old": {
        "primary": "#57b5b1",
        "secondary": "#ffccbc"
      },
      "oldschool": {
        "primary": "#2d76cc",
        "secondary": "#ef7200",
        "tertiary": "#ffccbc"
      },
      "outdoors": {
        "primary": "#00b459",
        "secondary": "#a8f36a"
      },
      "party": {
        "primary": "#9100ff",
        "secondary": "#ffccbc"
      },
      "patio": {
        "primary": "#fded35",
        "secondary": "#a8f36a"
      },
      "passionate": {
        "primary": "#ff6434",
        "secondary": "#ff5722"
      },
      "peaceful": {
        "primary": "#54ff95",
        "secondary": "#57b5b1"
      },
      "playful": {
        "primary": "#00cec8",
        "secondary": "#a8f36a",
        "tertiary": "#00cec8"
      },
      "playtime": {
        "primary": "#00cec8",
        "secondary": "#a8f36a",
        "tertiary": "#00cec8"
      },
      "popular": {
        "primary": "#e779b8",
        "secondary": "#ffc947"
      },
      "proud": {
        "primary": "#e779b8",
        "secondary": "#ffc947"
      },
      "positive": {
        "primary": "#fdff00",
        "secondary": "#ffc947"
      },
      "quiet": {
        "primary": "#e5d0ff",
        "secondary": "#57b5b1"
      },
      "quiet_energy": {
        "primary": "#3cd8ff",
        "secondary": "#cef4d1",
        "tertiary": "#ffffe4"
      },
      "radical": {
        "primary": "#ff00ff",
        "secondary": "#fdff00"
      },
      "relaxing": {
        "primary": "#2d76cc",
        "secondary": "#c4f7f4"
      },
      "retro": {
        "primary": "#d391fa",
        "secondary": "#ffccbc"
      },
      "romantic": {
        "primary": "#ff0000",
        "secondary": "#e5d0ff"
      },
      "rousing": {
        "primary": "#c4f7f4",
        "secondary": "#f1ffcf"
      },
      "scenic": {
        "primary": "#58e86b",
        "secondary": "#c4f7f4"
      },
      "sensual": {
        "primary": "#7e1a65",
        "secondary": "#ffccbc"
      },
      "serene": {
        "primary": "#d4ffdc",
        "secondary": "#fded35"
      },
      "shimmy": {
        "primary": "#e5d0ff",
        "secondary": "#fded35"
      },
      "sleepy": {
        "primary": "#57b5b1",
        "secondary": "#5172bf"
      },
      "social": {
        "primary": "#9100ff",
        "secondary": "#f1ffcf",
        "tertiary": "#ffccbc"
      },
      "solidarity": {
        "primary": "#9100ff",
        "secondary": "#00ffe4",
        "tertiary": "#fff3e0"
      },
      "spiritual": {
        "primary": "#3e00b3",
        "secondary": "#f4e4db"
      },
      "spontaneous": {
        "primary": "#e5d0ff",
        "secondary": "#f4e4db"
      },
      "together": {
        "primary": "#ff0000",
        "secondary": "#ffccbc",
        "tertiary": "#f1ffcf"
      },
      "trendy": {
        "primary": "#ff6434",
        "secondary": "#e5d0ff"
      },
      "trending": {
        "primary": "#ffc947",
        "secondary": "#d391fa"
      },
      "tropical": {
        "primary": "#61ecb2",
        "secondary": "#fdff00"
      },
      "trust": {
        "primary": "#ffc947",
        "secondary": "#e779b8"
      },
      "underground": {
        "primary": "#205273",
        "secondary": "#7e1a65"
      },
      "unique": {
        "primary": "#0000ff",
        "secondary": "#e5d0ff"
      },
      "vibrant": {
        "primary": "#9100ff",
        "secondary": "#ffccbc"
      },
      "vintage": {
        "primary": "#61ecb2",
        "secondary": "#f1ffcf"
      },
      "volunteer": {
        "primary": "#ffc947",
        "secondary": "#a8f36a"
      },
      "whimsical": {
        "primary": "#00cec8",
        "secondary": "#fff3e0"
      },
      "wild": {
        "primary": "#64ff00",
        "secondary": "#f1ffcf"
      },
      "wistful": {
        "primary": "#ffc947",
        "secondary": "#f4e4db"
      },
      "witchy": {
        "primary": "#7e1a65",
        "secondary": "#d391fa"
      },
      "witty": {
        "primary": "#205273",
        "secondary": "#a0e5f7"
      },
      "zen": {
        "primary": "#57b5b1",
        "secondary": "#2d76cc"
      }
    },
    "gradients": {
      "quiet_energy": "#57b5b1 #d391fa"
    },
    "text": {
      "dark": "#3c3b3f",
      "muted": "#535156",
      "light": "#d1d0d8"
    },
    "ui": {
      "button": {
        "active": "#3c3b3f",
        "disabled": "#9999a3"
      },
      "tab": {
        "active": "#3c3b3f",
        "disabled": "#b2b1bc"
      }
    }
  },
  "column": {
    "gap": {
      "desktop": "1.5rem",
      "mobile": "0.5rem",
      "list": "1.75rem"
    }
  },
  "line-height": {
    "tall": 1.8,
    "large": 1.6,
    "base": 1.2,
    "small": 1,
    "none": 0
  },
  "margin": {
    "center": "0 auto"
  },
  "padding": {
    "item": "2.5rem",
    "section": "3.5rem"
  },
  "post": {
    "text": {
      "block": {
        "heading": 30,
        "subheading": 18
      },
      "card": {
        "title": 20,
        "description": 14,
        "category": 16
      },
      "caption": 16,
      "category": 18,
      "cite": 16,
      "heading": {
        "title": 36,
        "subheading": 30,
        "heading1": 36,
        "heading2": 34,
        "heading3": 30,
        "heading4": 26,
        "heading5": 20,
        "heading6": 18
      },
      "list": 18,
      "info": 16,
      "paragraph": 18,
      "pullquote": 32
    }
  },
  "transitions": {
    "base": {
      "default": "0.35s ease !default"
    }
  },
  "font": {
    "family": {
      "sans": "Public Sans",
      "serif": "Nantes"
    },
    "height": {
      "base": 1.2,
      "large": 1.6,
      "small": 1,
      "tall": 1.8,
      "none": 0
    },
    "size": {
      "base": 16,
      "normal": 16,
      "small": 14,
      "tiny": 12,
      "micro": 10,
      "large": 18
    },
    "weight": {
      "base": 300,
      "light": 200,
      "normal": 300,
      "link": 400,
      "medium": 500,
      "bold": 700
    }
  },
  "units": {
    "base": {
      "base": 4,
      "huge": 12,
      "large": 8,
      "nano": 0.4,
      "small": 2,
      "tiny": 1
    }
  }
}